pywebtop-0.0.1.dist-info/licenses/LICENSE
webtop/__init__.py
webtop/client.py
webtop/exceptions.py
webtop/models.py
pywebtop-0.0.1.dist-info/METADATA
pywebtop-0.0.1.dist-info/WHEEL
pywebtop-0.0.1.dist-info/top_level.txt
pywebtop-0.0.1.dist-info/RECORD
