Metadata-Version: 2.4
Name: pywebtop
Version: 0.0.1
Summary: Unofficial async Python API wrapper for Webtop (SmartSchool)
Home-page: https://github.com/t0mer/pywebtop
Download-URL: https://pypi.org/project/pywebtop/
Author: Tomer Klein
Author-email: tomer.klein@gmail.com
License: MIT
Keywords: webtop,smartschool,education,api,async
Classifier: Development Status :: 3 - Alpha
Classifier: Intended Audience :: Developers
Classifier: Topic :: Education
Classifier: Topic :: Software Development :: Libraries
Classifier: Framework :: AsyncIO
Classifier: License :: OSI Approved :: MIT License
Classifier: Programming Language :: Python :: 3
Classifier: Programming Language :: Python :: 3.8
Classifier: Programming Language :: Python :: 3.9
Classifier: Programming Language :: Python :: 3.10
Classifier: Programming Language :: Python :: 3.11
Classifier: Operating System :: OS Independent
Requires-Python: >=3.8
License-File: LICENSE
Requires-Dist: httpx<1.0,>=0.25
Dynamic: author
Dynamic: author-email
Dynamic: classifier
Dynamic: description
Dynamic: description-content-type
Dynamic: download-url
Dynamic: home-page
Dynamic: keywords
Dynamic: license
Dynamic: license-file
Dynamic: requires-dist
Dynamic: requires-python
Dynamic: summary
